ml_research_tools/__init__.py
ml_research_tools/__main__.py
ml_research_tools/cache/README.md
ml_research_tools/cache/__init__.py
ml_research_tools/cache/redis.py
ml_research_tools/core/__init__.py
ml_research_tools/core/base_tool.py
ml_research_tools/core/config.py
ml_research_tools/core/llm_tools.py
ml_research_tools/core/logging_tools.py
ml_research_tools/core/service_factories.py
ml_research_tools/core/service_provider.py
ml_research_tools/doc/__init__.py
ml_research_tools/doc/ask_document_tool.py
ml_research_tools/exp/__init__.py
ml_research_tools/exp/wandb_downloader_tool.py
ml_research_tools/kube/__init__.py
ml_research_tools/kube/pod_forward_tool.py
ml_research_tools/tex/__init__.py
ml_research_tools/tex/backend/__init__.py
ml_research_tools/tex/backend/svg_patch.py
ml_research_tools/tex/latex_grammar_tool.py
ml_research_tools/tex/presets/__init__.py
ml_research_tools/tex/presets/nice_figures.py
ml_research_tools/tex/presets/save.py
ml_research_tools/tex/presets/sizes.py
ml_research_tools/tex/presets/tools.py
ml_research_tools-1.1.0.dist-info/LICENSE
ml_research_tools-1.1.0.dist-info/METADATA
ml_research_tools-1.1.0.dist-info/WHEEL
ml_research_tools-1.1.0.dist-info/entry_points.txt
ml_research_tools-1.1.0.dist-info/RECORD
