Metadata-Version: 2.3
Name: ml_research_tools
Version: 1.1.0
Summary: A collection of tools for machine learning research, including experiment management, Kubernetes utilities, and LaTeX processing.
License: MIT
Author: alexdremov
Author-email: dremov.me@gmail.com
Requires-Python: >=3.10
Classifier: Development Status :: 4 - Beta
Classifier: Intended Audience :: Science/Research
Classifier: License :: OSI Approved :: MIT License
Classifier: Programming Language :: Python :: 3
Classifier: Programming Language :: Python :: 3.10
Classifier: Programming Language :: Python :: 3.11
Classifier: Programming Language :: Python :: 3.12
Classifier: Topic :: Scientific/Engineering :: Artificial Intelligence
Requires-Dist: configparser (>=7.2.0,<8.0.0)
Requires-Dist: matplotlib (>=3.10.1,<4.0.0)
Requires-Dist: numpy (>=2.2.4,<3.0.0)
Requires-Dist: openai (>=1.68.2,<2.0.0)
Requires-Dist: pandas (>=2.2.3,<3.0.0)
Requires-Dist: pypdf2 (>=3.0.1)
Requires-Dist: pyyaml (>=6.0.2,<7.0.0)
Requires-Dist: redis (>=5.2.1,<6.0.0)
Requires-Dist: rich (>=13.9.4,<14.0.0)
Requires-Dist: rich-argparse (>=1.7.0,<2.0.0)
Requires-Dist: tenacity (>=9.0.0,<10.0.0)
Requires-Dist: tiktoken (>=0.9.0,<0.10.0)
Requires-Dist: tqdm (>=4.67.1,<5.0.0)
Requires-Dist: typer (>=0.15.2,<0.16.0)
Requires-Dist: typer-cli (>=0.15.2,<0.16.0)
Requires-Dist: typing-extensions (>=4.12.2,<5.0.0)
Requires-Dist: wandb (>=0.19.8,<0.20.0)
Project-URL: Bug Tracker, https://github.com/alexdremov/ml_research_tools/issues
Project-URL: Documentation, https://alexdremov.github.io/ml_research_tools/
Project-URL: Repository, https://github.com/alexdremov/ml_research_tools
